pyld/__init__.py
pyld/common.py
pyld/elements.py
pyld/ladder.py
py_ladder_diagram-0.0.1.dist-info/LICENSE
py_ladder_diagram-0.0.1.dist-info/WHEEL
py_ladder_diagram-0.0.1.dist-info/METADATA
py_ladder_diagram-0.0.1.dist-info/RECORD
